{
  "UserAgent": "MobileHub/1.0",
  "Version": "1.0",
  "CredentialsProvider": {
    "CognitoIdentity": {
      "Default": {
        "PoolId": "eu-west-1:dfa11695-0291-464e-bbae-3a061d6c4c84",
        "Region": "eu-west-1"
      }
    }
  },
  "IdentityManager": {
    "Default": {}
  },
  "S3TransferUtility": {
    "Default": {
      "Bucket": "itutor-userfiles-mobilehub-1829117854",
      "Region": "eu-west-1"
    }
  },
  "PinpointAnalytics": {
    "Default": {
      "AppId": "a098896df9f441b8a2cdb3066c9d2697",
      "Region": "us-east-1"
    }
  },
  "PinpointTargeting": {
    "Default": {
      "Region": "us-east-1"
    }
  },
  "UserFileManager": {
    "Default": {
      "Bucket": "itutor-userfiles-mobilehub-1829117854",
      "Region": "eu-west-1"
    }
  }
}